[
  {
    "id": 1,
    "title": "Azure Heights Luxury Residences",
    "image": "../images/Rectangle 48623.png",
    "location": "Dubai Marina",
    "price": "from $290k",
    "installmentPlan": "from $290k",
    "initialPayment": "$30,000",
    "upgradedFeatures": ["roller", "chair"],
    "completionDate": "09/2025"
  },
  {
    "id": 2,
    "title": "Azure Heights Luxury Residences",
    "image": "./images/Rectangle 48624.png",
    "location": "Dubai Marina",
    "price": "from $290k",
    "installmentPlan": "from $290k",
    "initialPayment": "$30,000",
    "upgradedFeatures": ["roller", "chair"],
    "completionDate": "09/2025"
  },
  {
    "id": 3,
    "title": "Azure Heights Luxury Residences",
    "image": "./images/Rectangle 48625.png",
    "location": "Dubai Marina",
    "price": "from $290k",
    "installmentPlan": "from $290k",
    "initialPayment": "$30,000",
    "upgradedFeatures": ["roller", "chair"],
    "completionDate": "09/2025"
  },
  {
    "id": 4,
    "title": "Azure Heights Luxury Residences",
    "image": "./images/Rectangle 48626.png",
    "location": "Dubai Marina",
    "price": "from $290k",
    "installmentPlan": "from $290k",
    "initialPayment": "$30,000",
    "upgradedFeatures": ["roller", "chair"],
    "completionDate": "09/2025"
  },
  {
    "id": 5,
    "title": "Azure Heights Luxury Residences",
    "image": "./images/Rectangle 48627.png",
    "location": "Dubai Marina",
    "price": "from $290k",
    "installmentPlan": "from $290k",
    "initialPayment": "$30,000",
    "upgradedFeatures": ["roller", "chair"],
    "completionDate": "09/2025"
  }
]
